cloudcoil/models/knative_serving/__init__.py
cloudcoil/models/knative_serving/py.typed
cloudcoil/models/knative_serving/internal/autoscaling/__init__.py
cloudcoil/models/knative_serving/internal/autoscaling/v1alpha1.py
cloudcoil/models/knative_serving/internal/caching/__init__.py
cloudcoil/models/knative_serving/internal/caching/v1alpha1.py
cloudcoil/models/knative_serving/internal/networking/__init__.py
cloudcoil/models/knative_serving/internal/networking/v1alpha1.py
cloudcoil/models/knative_serving/serving/__init__.py
cloudcoil/models/knative_serving/serving/v1.py
cloudcoil/models/knative_serving/serving/v1beta1.py
cloudcoil_models_knative_serving-1.17.0.0.dist-info/METADATA
cloudcoil_models_knative_serving-1.17.0.0.dist-info/WHEEL
cloudcoil_models_knative_serving-1.17.0.0.dist-info/licenses/LICENSE
cloudcoil_models_knative_serving-1.17.0.0.dist-info/RECORD
