Metadata-Version: 2.4
Name: cloudcoil.models.knative_serving
Version: 1.17.0.0
Summary: Versioned knative-serving models for cloudcoil
Project-URL: Homepage, https://github.com/cloudcoil/cloudcoil
Project-URL: Documentation, https://cloudcoil.github.io/cloudcoil
Project-URL: Repository, https://github.com/cloudcoil/models-knative-serving
Project-URL: Issues, https://github.com/cloudcoil/models-knative-serving/issues
Project-URL: Changelog, https://github.com/cloudcoil/models-knative-serving/releases
Author-email: Sambhav Kothari <sambhavs.email@gmail.com>
Maintainer-email: Sambhav Kothari <sambhavs.email@gmail.com>
License: Apache-2.0
License-File: LICENSE
Keywords: async,cloud-native,cloudcoil,cloudcoil-models,knative-serving,kubernetes,pydantic,python
Classifier: Programming Language :: Python :: 3.10
Classifier: Programming Language :: Python :: 3.11
Classifier: Programming Language :: Python :: 3.12
Classifier: Programming Language :: Python :: 3.13
Requires-Python: >=3.10
Requires-Dist: cloudcoil>=0.4.0
